api/__init__.py
fund/__init__.py
fund/getter.py
stock/__init__.py
stock/getter.py
twshare/__init__.py
twshare/main.py
twshare/api/__init__.py
twshare/fund/__init__.py
twshare/fund/getter.py
twshare/stock/__init__.py
twshare/stock/getter.py
twshare-1.3.dist-info/METADATA
twshare-1.3.dist-info/WHEEL
twshare-1.3.dist-info/top_level.txt
twshare-1.3.dist-info/RECORD
